<?xml version="1.0" encoding="UTF-8"?>
<billStatus>
  <bill>
    <relatedBills>
      <item>
        <congress>115</congress>
        <latestTitle>Financial CHOICE Act of 2017</latestTitle>
        <type>HR</type>
        <relationshipDetails>
          <item>
            <identifiedBy>CRS</identifiedBy>
            <type>Related bill</type>
          </item>
        </relationshipDetails>
        <latestAction>
          <text>Committee on Banking, Housing, and Urban Affairs. Hearings held. Hearings printed: S.Hrg. 115-108.</text>
          <actionDate>2017-07-13</actionDate>
        </latestAction>
        <number>10</number>
      </item>
      <item>
        <congress>115</congress>
        <latestTitle>Providing for consideration of the bill (H.R. 2201) to amend the Securities Act of 1933 to exempt certain micro-offerings from the registration requirements of such Act, and for other purposes.</latestTitle>
        <type>HRES</type>
        <relationshipDetails>
          <item>
            <identifiedBy>House</identifiedBy>
            <type>Procedurally-related</type>
          </item>
        </relationshipDetails>
        <latestAction>
          <text>Motion to reconsider laid on the table Agreed to without objection.</text>
          <actionTime>13:35:24</actionTime>
          <actionDate>2017-11-08</actionDate>
        </latestAction>
        <number>609</number>
      </item>
    </relatedBills>
    <calendarNumbers>
      <item>
        <calendar>U00280</calendar>
        <number />
      </item>
    </calendarNumbers>
    <billType>HR</billType>
    <title>Micro Offering Safe Harbor Act</title>
    <introducedDate>2017-04-27</introducedDate>
    <titles>
      <item>
        <title>Micro Offering Safe Harbor Act</title>
        <parentTitleType>Short Titles House of Representatives</parentTitleType>
        <titleType>Short Titles as Passed House</titleType>
        <chamberCode>H</chamberCode>
        <chamberName>House</chamberName>
      </item>
      <item>
        <title>Micro Offering Safe Harbor Act</title>
        <parentTitleType>Short Titles House of Representatives</parentTitleType>
        <titleType>Short Titles as Reported to House</titleType>
        <chamberCode>H</chamberCode>
        <chamberName>House</chamberName>
      </item>
      <item>
        <title>Micro Offering Safe Harbor Act</title>
        <parentTitleType />
        <titleType>Short Titles as Introduced</titleType>
        <chamberCode />
        <chamberName />
      </item>
      <item>
        <title>To amend the Securities Act of 1933 to exempt certain micro-offerings from the registration requirements of such Act, and for other purposes.</title>
        <parentTitleType />
        <titleType>Official Title as Introduced</titleType>
        <chamberCode />
        <chamberName />
      </item>
      <item>
        <title>Micro Offering Safe Harbor Act</title>
        <parentTitleType />
        <titleType>Display Title</titleType>
        <chamberCode />
        <chamberName />
      </item>
      <item>
        <title>Micro Offering Safe Harbor Act</title>
        <parentTitleType />
        <titleType>(Extracted from GPO) Short Titles as Passed House</titleType>
        <chamberCode>H</chamberCode>
        <chamberName>House</chamberName>
      </item>
      <item>
        <title>Micro Offering Safe Harbor Act</title>
        <parentTitleType />
        <titleType>(Extracted from GPO) Short Titles as Reported to House</titleType>
        <chamberCode>H</chamberCode>
        <chamberName>House</chamberName>
      </item>
      <item>
        <title>Micro Offering Safe Harbor Act</title>
        <parentTitleType />
        <titleType>(Extracted from GPO) Short Titles as Introduced</titleType>
        <chamberCode />
        <chamberName />
      </item>
    </titles>
    <latestAction>
      <actionDate>2017-11-13</actionDate>
      <text>Received in the Senate and Read twice and referred to the Committee on Banking, Housing, and Urban Affairs.</text>
      <links />
    </latestAction>
    <originChamber>House</originChamber>
    <actions>
      <actionTypeCounts>
        <referredToCommittee>1</referredToCommittee>
        <passageOfAMeasure>1</passageOfAMeasure>
        <unionCalendarAssignment>1</unionCalendarAssignment>
        <billReferrals>1</billReferrals>
        <actionStageOverride>2</actionStageOverride>
        <considerationByHouse>2</considerationByHouse>
        <ruleForConsiderationOfBillReportedToHouse>1</ruleForConsiderationOfBillReportedToHouse>
        <generalDebate>5</generalDebate>
        <motionToReconsiderResults>1</motionToReconsiderResults>
        <introducedInTheHouse>1</introducedInTheHouse>
        <placeholderTextForH>1</placeholderTextForH>
        <placeholderTextForHL>1</placeholderTextForHL>
        <committeeReportOfABill>1</committeeReportOfABill>
        <introducedInHouse>1</introducedInHouse>
        <reportedToHouse>1</reportedToHouse>
        <passedAgreedToInHouse>1</passedAgreedToInHouse>
      </actionTypeCounts>
      <item>
        <actionDate>2017-11-13</actionDate>
        <committee>
          <systemCode>ssbk00</systemCode>
          <name>Banking, Housing, and Urban Affairs Committee</name>
        </committee>
        <links />
        <sourceSystem>
          <code>0</code>
          <name>Senate</name>
        </sourceSystem>
        <text>Received in the Senate and Read twice and referred to the Committee on Banking, Housing, and Urban Affairs.</text>
        <type>IntroReferral</type>
      </item>
      <item>
        <sourceSystem>
          <code>2</code>
          <name>House floor actions</name>
        </sourceSystem>
        <actionTime>11:23:14</actionTime>
        <type>Floor</type>
        <actionDate>2017-11-09</actionDate>
        <links />
        <committee />
        <text>Motion to reconsider laid on the table Agreed to without objection.</text>
        <actionCode>H38310</actionCode>
      </item>
      <item>
        <sourceSystem>
          <code>2</code>
          <name>House floor actions</name>
        </sourceSystem>
        <actionTime>11:23:12</actionTime>
        <type>Floor</type>
        <actionDate>2017-11-09</actionDate>
        <links>
          <link>
            <url>http://clerk.house.gov/evs/2017/roll622.xml</url>
            <name>Roll no. 622</name>
          </link>
        </links>
        <committee />
        <text>On passage Passed by the Yeas and Nays: 232 - 188 (Roll no. 622).</text>
        <actionCode>H37100</actionCode>
      </item>
      <item>
        <sourceSystem>
          <code>9</code>
          <name>Library of Congress</name>
        </sourceSystem>
        <actionTime>11:23:12</actionTime>
        <type>Floor</type>
        <actionDate>2017-11-09</actionDate>
        <links>
          <link>
            <url>http://clerk.house.gov/evs/2017/roll622.xml</url>
            <name>Roll no. 622</name>
          </link>
        </links>
        <committee />
        <text>Passed/agreed to in House: On passage Passed by the Yeas and Nays: 232 - 188 (Roll no. 622).</text>
        <actionCode>8000</actionCode>
      </item>
      <item>
        <sourceSystem>
          <code>2</code>
          <name>House floor actions</name>
        </sourceSystem>
        <actionTime>10:44:53</actionTime>
        <type>Floor</type>
        <actionDate>2017-11-09</actionDate>
        <links>
          <link>
            <url>https://www.congress.gov/congressional-record/volume-163/house-section/page/H8678-8679</url>
            <name>H8678-8679</name>
          </link>
        </links>
        <committee />
        <text>Considered as unfinished business. (consideration: CR H8678-8679)</text>
        <actionCode>H30000</actionCode>
      </item>
      <item>
        <sourceSystem>
          <code>2</code>
          <name>House floor actions</name>
        </sourceSystem>
        <actionTime>10:30:08</actionTime>
        <type>Floor</type>
        <actionDate>2017-11-09</actionDate>
        <links>
          <link>
            <url>https://www.congress.gov/bill/115th-congress/house-bill/2201</url>
            <name>H.R. 2201</name>
          </link>
        </links>
        <committee />
        <text>POSTPONED PROCEEDINGS - At the conclusion of debate on H.R. 2201, the Chair put the question on passage and by voice vote, announced the ayes had prevailed. Ms. Maxine Waters (CA) demanded the yeas and nays and the Chair postponed further proceedings on the question of passage until a time to be announced.</text>
        <actionCode>H8D000</actionCode>
      </item>
      <item>
        <sourceSystem>
          <code>2</code>
          <name>House floor actions</name>
        </sourceSystem>
        <actionTime>10:22:34</actionTime>
        <type>Floor</type>
        <actionDate>2017-11-09</actionDate>
        <links>
          <link>
            <url>https://www.congress.gov/bill/115th-congress/house-resolution/609</url>
            <name>H.Res. 609</name>
          </link>
        </links>
        <committee />
        <text>DEBATE - Pursuant to the provisions of H.Res. 609, the House proceeded with 10 minutes of debate on the Emmer amendment.</text>
        <actionCode>H8D000</actionCode>
      </item>
      <item>
        <sourceSystem>
          <code>2</code>
          <name>House floor actions</name>
        </sourceSystem>
        <actionTime>09:44:00</actionTime>
        <type>Floor</type>
        <actionDate>2017-11-09</actionDate>
        <links>
          <link>
            <url>https://www.congress.gov/bill/115th-congress/house-bill/2201</url>
            <name>H.R. 2201</name>
          </link>
        </links>
        <committee />
        <text>DEBATE - The House resumed debate on H.R. 2201.</text>
        <actionCode>H8D000</actionCode>
      </item>
      <item>
        <sourceSystem>
          <code>2</code>
          <name>House floor actions</name>
        </sourceSystem>
        <actionTime>09:15:02</actionTime>
        <type>Floor</type>
        <actionDate>2017-11-09</actionDate>
        <links>
          <link>
            <url>https://www.congress.gov/bill/115th-congress/house-bill/2201</url>
            <name>H.R. 2201</name>
          </link>
        </links>
        <committee />
        <text>DEBATE - The House proceeded with one hour of debate on H.R. 2201.</text>
        <actionCode>H8D000</actionCode>
      </item>
      <item>
        <sourceSystem>
          <code>2</code>
          <name>House floor actions</name>
        </sourceSystem>
        <actionTime>09:14:31</actionTime>
        <type>Floor</type>
        <actionDate>2017-11-09</actionDate>
        <links>
          <link>
            <url>https://www.congress.gov/bill/115th-congress/house-bill/2201</url>
            <name>H.R. 2201</name>
          </link>
        </links>
        <committee />
        <text>Rule provides for consideration of H.R. 2201 with 1 hour of general debate. Previous question shall be considered as ordered without intervening motions except motion to recommit with or without instructions.</text>
        <actionCode>H8D000</actionCode>
      </item>
      <item>
        <sourceSystem>
          <code>2</code>
          <name>House floor actions</name>
        </sourceSystem>
        <actionTime>09:14:26</actionTime>
        <type>Floor</type>
        <actionDate>2017-11-09</actionDate>
        <links>
          <link>
            <url>https://www.congress.gov/bill/115th-congress/house-resolution/609</url>
            <name>H. Res. 609</name>
          </link>
          <link>
            <url>https://www.congress.gov/congressional-record/volume-163/house-section/page/H8667</url>
            <name>H8667</name>
          </link>
          <link>
            <url>https://www.congress.gov/congressional-record/volume-163/house-section/page/H8667-8678</url>
            <name>H8667-8678</name>
          </link>
        </links>
        <committee />
        <text>Considered under the provisions of rule H. Res. 609. (consideration: CR H8667-8678; text of measure as reported in House: CR H8667)</text>
        <actionCode>H30000</actionCode>
      </item>
      <item>
        <sourceSystem>
          <code>2</code>
          <name>House floor actions</name>
        </sourceSystem>
        <actionTime>13:35:24</actionTime>
        <type>Floor</type>
        <actionDate>2017-11-08</actionDate>
        <links>
          <link>
            <url>https://www.congress.gov/bill/115th-congress/house-resolution/609</url>
            <name>H. Res. 609</name>
          </link>
        </links>
        <committee />
        <text>Rule H. Res. 609 passed House.</text>
        <actionCode>H1L220</actionCode>
      </item>
      <item>
        <sourceSystem>
          <code>2</code>
          <name>House floor actions</name>
        </sourceSystem>
        <actionTime>15:53:56</actionTime>
        <type>Floor</type>
        <actionDate>2017-11-07</actionDate>
        <links>
          <link>
            <url>https://www.congress.gov/bill/115th-congress/house-resolution/609</url>
            <name>H. Res. 609</name>
          </link>
          <link>
            <url>https://www.congress.gov/bill/115th-congress/house-bill/2201</url>
            <name>H.R. 2201</name>
          </link>
        </links>
        <committee />
        <text>Rules Committee Resolution H. Res. 609 Reported to House. Rule provides for consideration of H.R. 2201 with 1 hour of general debate. Previous question shall be considered as ordered without intervening motions except motion to recommit with or without instructions.</text>
        <actionCode>H1L210</actionCode>
      </item>
      <item>
        <sourceSystem>
          <code>2</code>
          <name>House floor actions</name>
        </sourceSystem>
        <committee />
        <type>Calendars</type>
        <actionDate>2017-11-01</actionDate>
        <links />
        <text>Placed on the Union Calendar, Calendar No. 280.</text>
        <actionCode>H12410</actionCode>
      </item>
      <item>
        <sourceSystem>
          <code>2</code>
          <name>House floor actions</name>
        </sourceSystem>
        <committee>
          <systemCode>hsba00</systemCode>
          <name>Financial Services Committee</name>
        </committee>
        <type>Committee</type>
        <actionDate>2017-11-01</actionDate>
        <links>
          <link>
            <url>https://www.congress.gov/congressional-report/115th-congress/house-report/383</url>
            <name>H. Rept. 115-383</name>
          </link>
        </links>
        <text>Reported by the Committee on Financial Services. H. Rept. 115-383.</text>
        <actionCode>H12200</actionCode>
      </item>
      <item>
        <sourceSystem>
          <code>9</code>
          <name>Library of Congress</name>
        </sourceSystem>
        <committee>
          <systemCode>hsba00</systemCode>
          <name>Financial Services Committee</name>
        </committee>
        <type>Committee</type>
        <actionDate>2017-11-01</actionDate>
        <links>
          <link>
            <url>https://www.congress.gov/congressional-report/115th-congress/house-report/383</url>
            <name>H. Rept. 115-383</name>
          </link>
        </links>
        <text>Reported by the Committee on Financial Services. H. Rept. 115-383.</text>
        <actionCode>5000</actionCode>
      </item>
      <item>
        <actionDate>2017-10-12</actionDate>
        <committee>
          <systemCode>hsba00</systemCode>
          <name>Financial Services Committee</name>
        </committee>
        <links />
        <sourceSystem>
          <code>1</code>
          <name>House committee actions</name>
        </sourceSystem>
        <text>Ordered to be Reported by the Yeas and Nays: 34 - 26.</text>
        <type>Committee</type>
      </item>
      <item>
        <actionDate>2017-10-12</actionDate>
        <committee>
          <systemCode>hsba00</systemCode>
          <name>Financial Services Committee</name>
        </committee>
        <links />
        <sourceSystem>
          <code>1</code>
          <name>House committee actions</name>
        </sourceSystem>
        <text>Committee Consideration and Mark-up Session Held.</text>
        <type>Committee</type>
      </item>
      <item>
        <actionDate>2017-10-11</actionDate>
        <committee>
          <systemCode>hsba00</systemCode>
          <name>Financial Services Committee</name>
        </committee>
        <links />
        <sourceSystem>
          <code>1</code>
          <name>House committee actions</name>
        </sourceSystem>
        <text>Committee Consideration and Mark-up Session Held.</text>
        <type>Committee</type>
      </item>
      <item>
        <sourceSystem>
          <code>2</code>
          <name>House floor actions</name>
        </sourceSystem>
        <committee>
          <systemCode>hsba00</systemCode>
          <name>Financial Services Committee</name>
        </committee>
        <type>IntroReferral</type>
        <actionDate>2017-04-27</actionDate>
        <links />
        <text>Referred to the House Committee on Financial Services.</text>
        <actionCode>H11100</actionCode>
      </item>
      <item>
        <sourceSystem>
          <code>9</code>
          <name>Library of Congress</name>
        </sourceSystem>
        <committee />
        <type>IntroReferral</type>
        <actionDate>2017-04-27</actionDate>
        <links />
        <text>Introduced in House</text>
        <actionCode>Intro-H</actionCode>
      </item>
      <item>
        <sourceSystem>
          <code>9</code>
          <name>Library of Congress</name>
        </sourceSystem>
        <committee />
        <type>IntroReferral</type>
        <actionDate>2017-04-27</actionDate>
        <links />
        <text>Introduced in House</text>
        <actionCode>1000</actionCode>
      </item>
      <actionByCounts>
        <senate>1</senate>
        <houseOfRepresentatives>21</houseOfRepresentatives>
      </actionByCounts>
    </actions>
    <policyArea>
      <name>Finance and Financial Sector</name>
    </policyArea>
    <constitutionalAuthorityStatementText><![CDATA[<pre>[Congressional Record Volume 163, Number 72 (Thursday, April 27, 2017)]From the Congressional Record Online through the Government Publishing Office [<a href='http://www.gpo.gov'>www.gpo.gov</a>]By Mr. EMMER:H.R. 2201.Congress has the power to enact this legislation pursuantto the following:Article 1, Section 8[Page H2942]</pre>]]></constitutionalAuthorityStatementText>
    <subjects>
      <billSubjects>
        <legislativeSubjects>
          <item>
            <name>Securities</name>
          </item>
          <item>
            <name>State and local government operations</name>
          </item>
        </legislativeSubjects>
        <policyArea>
          <name>Finance and Financial Sector</name>
        </policyArea>
      </billSubjects>
    </subjects>
    <recordedVotes>
      <recordedVote>
        <date>2017-11-09T16:23:12Z</date>
        <chamber>House</chamber>
        <congress>115</congress>
        <url>http://clerk.house.gov/evs/2017/roll622.xml</url>
        <sessionNumber>1</sessionNumber>
        <fullActionName>Passage of a Measure</fullActionName>
        <rollNumber>622</rollNumber>
      </recordedVote>
    </recordedVotes>
    <cboCostEstimates>
      <item>
        <url>https://www.cbo.gov/publication/53268</url>
        <pubDate>2017-10-30T15:06:49Z</pubDate>
        <title>H.R. 2201, Micro Offering Safe Harbor Act</title>
      </item>
    </cboCostEstimates>
    <billNumber>2201</billNumber>
    <updateDate>2018-02-22T15:27:41Z</updateDate>
    <notes />
    <laws />
    <createDate>2017-04-28T03:11:52Z</createDate>
    <summaries>
      <billSummaries>
        <item>
          <actionDesc>Introduced in House</actionDesc>
          <versionCode>00</versionCode>
          <text><![CDATA[<p><strong>Micro Offering Safe Harbor Act</strong></p> <p>This bill&nbsp;amends the Securities Act of 1933 to&nbsp;exempt certain micro-offerings from: (1) state regulation of securities offerings, and (2) federal prohibitions&nbsp;related to&nbsp;interstate solicitation.</p>]]></text>
          <actionDate>2017-04-27</actionDate>
          <name>Introduced in House</name>
          <lastSummaryUpdateDate>2017-08-16T18:29:01Z</lastSummaryUpdateDate>
          <updateDate>2017-04-27T04:00:00Z</updateDate>
        </item>
        <item>
          <actionDesc>Reported to House without amendment</actionDesc>
          <versionCode>79</versionCode>
          <text><![CDATA[<p>(This measure has not been amended since it was introduced. The summary has been expanded because action occurred on the measure.)</p> <p><b>Micro Offering Safe Harbor Act</b></p> <p>(Sec. 2) This bill&nbsp;amends the Securities Act of 1933 to&nbsp;exempt certain micro-offerings from: (1) state regulation of securities offerings, and (2) federal prohibitions&nbsp;related to&nbsp;interstate solicitation. </p> <p>The exempted micro-offerings must meet all of the following requirements:</p> <ul> <li>the purchaser has a substantive pre-existing relationship with the issuer, </li> <li>during the 12-month period preceding the transaction there are no more than 35 purchasers relying on the exemption, and </li> <li>the amount of all securities sold by the issuer (including any amount sold in reliance upon the exemption) during the 12-month period preceding the transaction does not exceed $500,000.</li> </ul>]]></text>
          <actionDate>2017-11-01</actionDate>
          <name>Reported to House without amendment</name>
          <lastSummaryUpdateDate>2017-11-03T16:32:51Z</lastSummaryUpdateDate>
          <updateDate>2017-11-01T13:46:20Z</updateDate>
        </item>
      </billSummaries>
    </summaries>
    <amendments>
      <amendment>
        <createDate>2017-11-10T08:16:22Z</createDate>
        <number>482</number>
        <type>HAMDT</type>
        <updateDate>2018-02-22T15:27:41Z</updateDate>
        <submittedDate>2017-11-09T05:00:00Z</submittedDate>
        <proposedDate />
        <sponsors>
          <item>
            <district>6</district>
            <state>MN</state>
            <fullName>Rep. Emmer, Tom [R-MN-6]</fullName>
            <bioguideId>E000294</bioguideId>
            <firstName>Tom</firstName>
            <party>R</party>
            <middleName />
            <identifiers>
              <bioguideId>E000294</bioguideId>
              <gpoId />
              <lisID>2253</lisID>
            </identifiers>
            <lastName>Emmer</lastName>
          </item>
        </sponsors>
        <amendments>
          <count>0</count>
        </amendments>
        <congress>115</congress>
        <cosponsors>
          <totalCount>0</totalCount>
          <currentCount>0</currentCount>
        </cosponsors>
        <amendedAmendment />
        <amendedBill>
          <congress>115</congress>
          <number>2201</number>
          <type>HR</type>
          <originChamber>House</originChamber>
          <originChamberCode>H</originChamberCode>
          <title>Micro Offering Safe Harbor Act</title>
        </amendedBill>
        <links />
        <notes />
        <titles />
        <actions>
          <count>8</count>
          <actionByCounts>
            <houseOfRepresentatives>7</houseOfRepresentatives>
          </actionByCounts>
          <actions>
            <item>
              <actionDate>2017-11-09</actionDate>
              <text>On agreeing to the Emmer amendment (A001) Agreed to by voice vote.</text>
              <actionTime>10:29:15</actionTime>
              <sourceSystem>
                <code>2</code>
                <name>House floor actions</name>
              </sourceSystem>
              <committee />
              <links>
                <link>
                  <url>https://www.congress.gov/amendment/115th-congress/house-amendment/482</url>
                  <name>H.Amdt.482</name>
                </link>
              </links>
              <actionCode>H34111</actionCode>
              <type>Floor</type>
            </item>
            <item>
              <actionDate>2017-11-09</actionDate>
              <text>The previous question was ordered on the amendment and the bill pursuant to the rule.</text>
              <actionTime>10:29:04</actionTime>
              <sourceSystem>
                <code>2</code>
                <name>House floor actions</name>
              </sourceSystem>
              <committee />
              <links>
                <link>
                  <url>https://www.congress.gov/amendment/115th-congress/house-amendment/482</url>
                  <name>H.Amdt.482</name>
                </link>
              </links>
              <actionCode>H34180</actionCode>
              <type>Floor</type>
            </item>
            <item>
              <actionDate>2017-11-09</actionDate>
              <text>Amendment (A001) offered by Mr. Emmer. (consideration: CR H8677-8678; text: CR H8677)</text>
              <actionTime>10:22:31</actionTime>
              <sourceSystem>
                <code>2</code>
                <name>House floor actions</name>
              </sourceSystem>
              <committee />
              <links>
                <link>
                  <url>https://www.congress.gov/amendment/115th-congress/house-amendment/482</url>
                  <name>H.Amdt.482</name>
                </link>
                <link>
                  <url>https://www.congress.gov/congressional-record/volume-163/house-section/page/H8677</url>
                  <name>H8677</name>
                </link>
                <link>
                  <url>https://www.congress.gov/congressional-record/volume-163/house-section/page/H8677-8678</url>
                  <name>H8677-8678</name>
                </link>
              </links>
              <actionCode>H3A100</actionCode>
              <type>Floor</type>
            </item>
            <item>
              <actionDate>2017-11-09</actionDate>
              <committee />
              <links />
              <text />
            </item>
            <item>
              <actionDate>2017-11-09</actionDate>
              <text>House amendment offered/reported by : Amendment (A001) offered by Mr. Emmer.</text>
              <actionTime>10:22:31</actionTime>
              <sourceSystem>
                <code>9</code>
                <name>Library of Congress</name>
              </sourceSystem>
              <committee />
              <links>
                <link>
                  <url>https://www.congress.gov/amendment/115th-congress/house-amendment/482</url>
                  <name>H.Amdt.482</name>
                </link>
                <link>
                  <url>https://www.congress.gov/congressional-record/volume-163/house-section/page/H8677</url>
                  <name>H8677</name>
                </link>
                <link>
                  <url>https://www.congress.gov/congressional-record/volume-163/house-section/page/H8677-8678</url>
                  <name>H8677-8678</name>
                </link>
              </links>
              <actionCode>71500</actionCode>
              <type>NotUsed</type>
            </item>
            <item>
              <actionDate>2017-11-09</actionDate>
              <text>Amendment agreed to by House: On agreeing to the Emmer amendment (A001) Agreed to by voice vote.</text>
              <actionTime>10:29:15</actionTime>
              <sourceSystem>
                <code>9</code>
                <name>Library of Congress</name>
              </sourceSystem>
              <committee />
              <links>
                <link>
                  <url>https://www.congress.gov/amendment/115th-congress/house-amendment/482</url>
                  <name>H.Amdt.482</name>
                </link>
              </links>
              <actionCode>79000</actionCode>
              <type>NotUsed</type>
            </item>
            <item>
              <actionDate>2017-11-09</actionDate>
              <text>House amendment agreed to: On agreeing to the Emmer amendment (A001) Agreed to by voice vote.</text>
              <actionTime>10:29:15</actionTime>
              <sourceSystem>
                <code>9</code>
                <name>Library of Congress</name>
              </sourceSystem>
              <committee />
              <links>
                <link>
                  <url>https://www.congress.gov/amendment/115th-congress/house-amendment/482</url>
                  <name>H.Amdt.482</name>
                </link>
              </links>
              <actionCode>72000</actionCode>
              <type>Floor</type>
            </item>
            <item>
              <actionDate>2017-11-09</actionDate>
              <text>House amendment offered</text>
              <sourceSystem>
                <code>9</code>
                <name>Library of Congress</name>
              </sourceSystem>
              <committee />
              <type>Floor</type>
              <actionCode>71000</actionCode>
              <links />
            </item>
          </actions>
          <actionTypeCounts>
            <motionForThePreviousQuestionOffered>1</motionForThePreviousQuestionOffered>
            <houseAmendmentAgreedTo>1</houseAmendmentAgreedTo>
            <amendmentAgreedToByHouse>1</amendmentAgreedToByHouse>
            <houseAmendmentOfferedReportedBy>1</houseAmendmentOfferedReportedBy>
            <amendmentOffered>1</amendmentOffered>
            <houseAmendmentOffered>1</houseAmendmentOffered>
            <agreeingToTheAmendmentResults>1</agreeingToTheAmendmentResults>
          </actionTypeCounts>
        </actions>
        <purpose />
        <description>Page 3, line 14, strike "The transactions" and insert the following:    "(1) IN GENERAL- The transactions".    Page 3, line 19, strike "(1)" and insert "(A)" and adjust the margin 2 ems to the right. ***.</description>
        <chamber>House of Representatives</chamber>
        <version>1.0.0</version>
        <number>482</number>
        <description>Page 3, line 14, strike "The transactions" and insert the following:    "(1) IN GENERAL- The transactions".    Page 3, line 19, strike "(1)" and insert "(A)" and adjust the margin 2 ems to the right. ***.</description>
        <congress>115</congress>
        <latestAction>
          <actionDate>2017-11-09</actionDate>
          <actionTime>10:29:15</actionTime>
          <text>On agreeing to the Emmer amendment (A001) Agreed to by voice vote.</text>
        </latestAction>
        <purpose />
        <type>HAMDT</type>
      </amendment>
    </amendments>
    <committees>
      <billCommittees>
        <item>
          <subcommittees />
          <chamber>Senate</chamber>
          <activities>
            <item>
              <date>2017-11-13T21:37:17Z</date>
              <name>Referred to</name>
            </item>
          </activities>
          <type>Standing</type>
          <name>Banking, Housing, and Urban Affairs Committee</name>
          <systemCode>ssbk00</systemCode>
        </item>
        <item>
          <subcommittees />
          <chamber>House</chamber>
          <activities>
            <item>
              <date>2017-11-01T22:48:34Z</date>
              <name>Reported by</name>
            </item>
            <item>
              <date>2017-10-12T16:39:41Z</date>
              <name>Markup by</name>
            </item>
            <item>
              <date>2017-04-27T14:00:26Z</date>
              <name>Referred to</name>
            </item>
          </activities>
          <type>Standing</type>
          <name>Financial Services Committee</name>
          <systemCode>hsba00</systemCode>
        </item>
      </billCommittees>
    </committees>
    <cosponsors>
      <item>
        <sponsorshipDate>2017-09-06</sponsorshipDate>
        <state>OH</state>
        <firstName>Steve</firstName>
        <party>R</party>
        <identifiers>
          <bioguideId>S001187</bioguideId>
          <gpoId>8105</gpoId>
          <lisID>2047</lisID>
        </identifiers>
        <bioguideId>S001187</bioguideId>
        <sponsorshipWithdrawnDate />
        <isOriginalCosponsor>False</isOriginalCosponsor>
        <district>15</district>
        <fullName>Rep. Stivers, Steve [R-OH-15]</fullName>
        <lastName>Stivers</lastName>
        <middleName />
      </item>
      <item>
        <sponsorshipDate>2017-09-06</sponsorshipDate>
        <state>IN</state>
        <firstName>Luke</firstName>
        <party>R</party>
        <identifiers>
          <bioguideId>M001189</bioguideId>
          <gpoId />
          <lisID>2130</lisID>
        </identifiers>
        <bioguideId>M001189</bioguideId>
        <sponsorshipWithdrawnDate />
        <isOriginalCosponsor>False</isOriginalCosponsor>
        <district>6</district>
        <fullName>Rep. Messer, Luke [R-IN-6]</fullName>
        <lastName>Messer</lastName>
        <middleName />
      </item>
      <item>
        <sponsorshipDate>2017-09-06</sponsorshipDate>
        <state>CO</state>
        <firstName>Scott</firstName>
        <party>R</party>
        <identifiers>
          <bioguideId>T000470</bioguideId>
          <gpoId>7861</gpoId>
          <lisID>1997</lisID>
        </identifiers>
        <bioguideId>T000470</bioguideId>
        <sponsorshipWithdrawnDate />
        <isOriginalCosponsor>False</isOriginalCosponsor>
        <district>3</district>
        <fullName>Rep. Tipton, Scott  R. [R-CO-3]</fullName>
        <lastName>Tipton</lastName>
        <middleName>R.</middleName>
      </item>
      <item>
        <sponsorshipDate>2017-09-18</sponsorshipDate>
        <state>NC</state>
        <firstName>Robert</firstName>
        <party>R</party>
        <identifiers>
          <bioguideId>P000606</bioguideId>
          <lisID>2141</lisID>
          <gpoId />
        </identifiers>
        <bioguideId>P000606</bioguideId>
        <sponsorshipWithdrawnDate />
        <isOriginalCosponsor>False</isOriginalCosponsor>
        <district>9</district>
        <fullName>Rep. Pittenger, Robert [R-NC-9]</fullName>
        <lastName>Pittenger</lastName>
        <middleName />
      </item>
      <item>
        <sponsorshipDate>2017-09-27</sponsorshipDate>
        <state>NJ</state>
        <firstName>Thomas</firstName>
        <party>R</party>
        <identifiers>
          <bioguideId>M001193</bioguideId>
          <gpoId />
          <lisID>2258</lisID>
        </identifiers>
        <bioguideId>M001193</bioguideId>
        <sponsorshipWithdrawnDate />
        <isOriginalCosponsor>False</isOriginalCosponsor>
        <district>3</district>
        <fullName>Rep. MacArthur, Thomas [R-NJ-3]</fullName>
        <lastName>MacArthur</lastName>
        <middleName />
      </item>
    </cosponsors>
    <congress>115</congress>
    <committeeReports>
      <committeeReport>
        <citation>H. Rept. 115-383</citation>
      </committeeReport>
    </committeeReports>
    <version>1.0.0</version>
    <sponsors>
      <item>
        <lastName>Emmer</lastName>
        <district>6</district>
        <fullName>Rep. Emmer, Tom [R-MN-6]</fullName>
        <middleName />
        <bioguideId>E000294</bioguideId>
        <identifiers>
          <bioguideId>E000294</bioguideId>
          <gpoId />
          <lisID>2253</lisID>
        </identifiers>
        <byRequestType />
        <state>MN</state>
        <firstName>Tom</firstName>
        <party>R</party>
      </item>
    </sponsors>
  </bill>
  <dublinCore xmlns:dc="http://purl.org/dc/elements/1.1/">
    <dc:format>text/xml</dc:format>
    <dc:language>EN</dc:language>
    <dc:rights>Pursuant to Title 17 Section 105 of the United States Code, this file is not subject to copyright protection and is in the public domain.</dc:rights>
    <dc:contributor>Congressional Research Service, Library of Congress</dc:contributor>
    <dc:description>This file contains bill summaries and statuses for federal legislation. A bill summary describes the most significant provisions of a piece of legislation and details the effects the legislative text may have on current law and federal programs. Bill summaries are authored by the Congressional Research Service (CRS) of the Library of Congress. As stated in Public Law 91-510 (2 USC 166 (d)(6)), one of the duties of CRS is "to prepare summaries and digests of bills and resolutions of a public general nature introduced in the Senate or House of Representatives". For more information, refer to the User Guide that accompanies this file.</dc:description>
  </dublinCore>
</billStatus>

