<?xml version="1.0" encoding="UTF-8"?>
<billStatus>
  <bill>
    <constitutionalAuthorityStatementText />
    <originChamber>House</originChamber>
    <subjects>
      <billSubjects>
        <policyArea>
          <name>International Affairs</name>
        </policyArea>
        <legislativeSubjects>
          <item>
            <name>Asia</name>
          </item>
          <item>
            <name>China</name>
          </item>
          <item>
            <name>Human rights</name>
          </item>
          <item>
            <name>Racial and ethnic relations</name>
          </item>
          <item>
            <name>Religion</name>
          </item>
        </legislativeSubjects>
      </billSubjects>
    </subjects>
    <cosponsors>
      <item>
        <district>8</district>
        <sponsorshipWithdrawnDate />
        <party>R</party>
        <fullName>Rep. Franks, Trent [R-AZ-8]</fullName>
        <sponsorshipDate>2017-07-11</sponsorshipDate>
        <bioguideId>F000448</bioguideId>
        <middleName />
        <identifiers>
          <gpoId>7799</gpoId>
          <lisID>1707</lisID>
          <bioguideId>F000448</bioguideId>
        </identifiers>
        <lastName>Franks</lastName>
        <isOriginalCosponsor>True</isOriginalCosponsor>
        <firstName>Trent</firstName>
        <state>AZ</state>
      </item>
      <item>
        <district>5</district>
        <sponsorshipWithdrawnDate />
        <party>R</party>
        <fullName>Rep. Lamborn, Doug [R-CO-5]</fullName>
        <sponsorshipDate>2017-07-11</sponsorshipDate>
        <bioguideId>L000564</bioguideId>
        <middleName />
        <identifiers>
          <bioguideId>L000564</bioguideId>
          <gpoId>7863</gpoId>
          <lisID>1834</lisID>
        </identifiers>
        <lastName>Lamborn</lastName>
        <isOriginalCosponsor>True</isOriginalCosponsor>
        <firstName>Doug</firstName>
        <state>CO</state>
      </item>
      <item>
        <district>6</district>
        <sponsorshipWithdrawnDate />
        <party>R</party>
        <fullName>Rep. Grothman, Glenn [R-WI-6]</fullName>
        <sponsorshipDate>2017-07-11</sponsorshipDate>
        <bioguideId>G000576</bioguideId>
        <middleName />
        <identifiers>
          <lisID>2276</lisID>
          <gpoId />
          <bioguideId>G000576</bioguideId>
        </identifiers>
        <lastName>Grothman</lastName>
        <isOriginalCosponsor>True</isOriginalCosponsor>
        <firstName>Glenn</firstName>
        <state>WI</state>
      </item>
      <item>
        <district>6</district>
        <sponsorshipWithdrawnDate />
        <party>R</party>
        <fullName>Rep. Roskam, Peter J. [R-IL-6]</fullName>
        <sponsorshipDate>2017-07-11</sponsorshipDate>
        <bioguideId>R000580</bioguideId>
        <middleName>J.</middleName>
        <identifiers>
          <gpoId>7926</gpoId>
          <lisID>1848</lisID>
          <bioguideId>R000580</bioguideId>
        </identifiers>
        <lastName>Roskam</lastName>
        <isOriginalCosponsor>True</isOriginalCosponsor>
        <firstName>Peter</firstName>
        <state>IL</state>
      </item>
      <item>
        <district>4</district>
        <sponsorshipWithdrawnDate />
        <party>R</party>
        <fullName>Rep. King, Steve [R-IA-4]</fullName>
        <sponsorshipDate>2017-07-11</sponsorshipDate>
        <bioguideId>K000362</bioguideId>
        <middleName />
        <identifiers>
          <bioguideId>K000362</bioguideId>
          <lisID>1724</lisID>
          <gpoId>7918</gpoId>
        </identifiers>
        <lastName>King</lastName>
        <isOriginalCosponsor>True</isOriginalCosponsor>
        <firstName>Steve</firstName>
        <state>IA</state>
      </item>
      <item>
        <district>14</district>
        <sponsorshipWithdrawnDate />
        <party>R</party>
        <fullName>Rep. Hultgren, Randy [R-IL-14]</fullName>
        <sponsorshipDate>2017-07-11</sponsorshipDate>
        <bioguideId>H001059</bioguideId>
        <middleName />
        <identifiers>
          <bioguideId>H001059</bioguideId>
          <lisID>2015</lisID>
          <gpoId>7934</gpoId>
        </identifiers>
        <lastName>Hultgren</lastName>
        <isOriginalCosponsor>True</isOriginalCosponsor>
        <firstName>Randy</firstName>
        <state>IL</state>
      </item>
    </cosponsors>
    <billType>HRES</billType>
    <recordedVotes />
    <laws />
    <committeeReports />
    <actions>
      <actionTypeCounts>
        <introducedInTheHouse>1</introducedInTheHouse>
        <billReferrals>1</billReferrals>
        <introducedInHouse>1</introducedInHouse>
        <placeholderTextForH>2</placeholderTextForH>
      </actionTypeCounts>
      <item>
        <actionDate>2017-09-05</actionDate>
        <committee>
          <systemCode>hsfa05</systemCode>
          <name>Asia and the Pacific Subcommittee</name>
        </committee>
        <links />
        <sourceSystem>
          <name>House committee actions</name>
          <code>1</code>
        </sourceSystem>
        <text>Referred to the Subcommittee on Asia and the Pacific.</text>
        <type>Committee</type>
      </item>
      <item>
        <actionDate>2017-09-05</actionDate>
        <committee>
          <systemCode>hsfa16</systemCode>
          <name>Africa, Global Health, Global Human Rights and International Organizations Subcommittee</name>
        </committee>
        <links />
        <sourceSystem>
          <name>House committee actions</name>
          <code>1</code>
        </sourceSystem>
        <text>Referred to the Subcommittee on Africa, Global Health, Global Human Rights and International Organizations.</text>
        <type>Committee</type>
      </item>
      <item>
        <type>IntroReferral</type>
        <links />
        <text>Referred to the House Committee on Foreign Affairs.</text>
        <committee>
          <systemCode>hsfa00</systemCode>
          <name>Foreign Affairs Committee</name>
        </committee>
        <actionDate>2017-07-11</actionDate>
        <sourceSystem>
          <name>House floor actions</name>
          <code>2</code>
        </sourceSystem>
        <actionCode>H11100</actionCode>
      </item>
      <item>
        <type>IntroReferral</type>
        <links />
        <text>Introduced in House</text>
        <committee />
        <actionDate>2017-07-11</actionDate>
        <sourceSystem>
          <name>Library of Congress</name>
          <code>9</code>
        </sourceSystem>
        <actionCode>Intro-H</actionCode>
      </item>
      <item>
        <type>IntroReferral</type>
        <links />
        <text>Introduced in House</text>
        <committee />
        <actionDate>2017-07-11</actionDate>
        <sourceSystem>
          <name>Library of Congress</name>
          <code>9</code>
        </sourceSystem>
        <actionCode>1000</actionCode>
      </item>
      <actionByCounts>
        <houseOfRepresentatives>5</houseOfRepresentatives>
      </actionByCounts>
    </actions>
    <createDate>2017-07-12T03:11:32Z</createDate>
    <version>1.0.0</version>
    <notes />
    <latestAction>
      <actionDate>2017-09-05</actionDate>
      <text>Referred to the Subcommittee on Asia and the Pacific.</text>
      <links />
    </latestAction>
    <title>Condemning violence against religious minorities in the People's Republic of China and any actions that limit the free expression and practice of faith by these minorities.</title>
    <summaries>
      <billSummaries>
        <item>
          <versionCode>00</versionCode>
          <text><![CDATA[<p>Condemns violence against religious minorities in the People's Republic of China and any actions that limit their free expression and practice of faith.</p> <p>Reaffirms the U.S. commitment to promoting religious freedom and tolerance around the world and helping to provide protection and relief to religious minorities facing persecution and violence.</p> <p>Calls on the Chinese government to uphold the Chinese Constitution in addition to the internationally recognized human right to freedom from religious persecution and to end all forms of violence and discrimination against religious minorities.</p> <p>Urges the President to take appropriate actions to promote religious freedom of religious minorities in China, using the powers provided under the International Religious Freedom Act of 1998 and the Frank R. Wolf International Religious Freedom Act.</p> <ul> </ul>]]></text>
          <actionDesc>Introduced in House</actionDesc>
          <actionDate>2017-07-11</actionDate>
          <lastSummaryUpdateDate>2017-09-28T20:47:01Z</lastSummaryUpdateDate>
          <name>Introduced in House</name>
          <updateDate>2017-07-11T04:00:00Z</updateDate>
        </item>
      </billSummaries>
    </summaries>
    <congress>115</congress>
    <policyArea>
      <name>International Affairs</name>
    </policyArea>
    <billNumber>434</billNumber>
    <calendarNumbers />
    <cboCostEstimates />
    <introducedDate>2017-07-11</introducedDate>
    <relatedBills />
    <committees>
      <billCommittees>
        <item>
          <systemCode>hsfa00</systemCode>
          <chamber>House</chamber>
          <type>Standing</type>
          <activities>
            <item>
              <date>2017-07-11T16:00:37Z</date>
              <name>Referred to</name>
            </item>
          </activities>
          <name>Foreign Affairs Committee</name>
          <subcommittees>
            <item>
              <activities>
                <item>
                  <date>2017-09-05T19:57:17Z</date>
                  <name>Referred to</name>
                </item>
              </activities>
              <systemCode>hsfa05</systemCode>
              <name>Asia and the Pacific Subcommittee</name>
            </item>
            <item>
              <activities>
                <item>
                  <date>2017-09-05T19:55:07Z</date>
                  <name>Referred to</name>
                </item>
              </activities>
              <systemCode>hsfa16</systemCode>
              <name>Africa, Global Health, Global Human Rights and International Organizations Subcommittee</name>
            </item>
          </subcommittees>
        </item>
      </billCommittees>
    </committees>
    <titles>
      <item>
        <chamberName />
        <titleType>Official Title as Introduced</titleType>
        <title>Condemning violence against religious minorities in the People's Republic of China and any actions that limit the free expression and practice of faith by these minorities.</title>
        <parentTitleType />
        <chamberCode />
      </item>
      <item>
        <chamberName />
        <titleType>Display Title</titleType>
        <title>Condemning violence against religious minorities in the People's Republic of China and any actions that limit the free expression and practice of faith by these minorities.</title>
        <parentTitleType />
        <chamberCode />
      </item>
    </titles>
    <sponsors>
      <item>
        <fullName>Rep. Hice, Jody B. [R-GA-10]</fullName>
        <middleName>B.</middleName>
        <district>10</district>
        <byRequestType />
        <firstName>Jody</firstName>
        <bioguideId>H001071</bioguideId>
        <state>GA</state>
        <party>R</party>
        <lastName>Hice</lastName>
        <identifiers>
          <gpoId />
          <bioguideId>H001071</bioguideId>
          <lisID>2237</lisID>
        </identifiers>
      </item>
    </sponsors>
    <updateDate>2018-02-06T16:39:52Z</updateDate>
    <amendments />
  </bill>
  <dublinCore xmlns:dc="http://purl.org/dc/elements/1.1/">
    <dc:format>text/xml</dc:format>
    <dc:language>EN</dc:language>
    <dc:rights>Pursuant to Title 17 Section 105 of the United States Code, this file is not subject to copyright protection and is in the public domain.</dc:rights>
    <dc:contributor>Congressional Research Service, Library of Congress</dc:contributor>
    <dc:description>This file contains bill summaries and statuses for federal legislation. A bill summary describes the most significant provisions of a piece of legislation and details the effects the legislative text may have on current law and federal programs. Bill summaries are authored by the Congressional Research Service (CRS) of the Library of Congress. As stated in Public Law 91-510 (2 USC 166 (d)(6)), one of the duties of CRS is "to prepare summaries and digests of bills and resolutions of a public general nature introduced in the Senate or House of Representatives". For more information, refer to the User Guide that accompanies this file.</dc:description>
  </dublinCore>
</billStatus>

